WallGo/__init__.py
WallGo/boltzmann.py
WallGo/collisionArray.py
WallGo/collisionHelpers.py
WallGo/config.py
WallGo/containers.py
WallGo/effectivePotential.py
WallGo/equationOfMotion.py
WallGo/exceptions.py
WallGo/fields.py
WallGo/freeEnergy.py
WallGo/genericModel.py
WallGo/grid.py
WallGo/grid3Scales.py
WallGo/helpers.py
WallGo/hydrodynamics.py
WallGo/hydrodynamicsTemplateModel.py
WallGo/interpolatableFunction.py
WallGo/manager.py
WallGo/mathematicaHelpers.py
WallGo/particle.py
WallGo/polynomial.py
WallGo/results.py
WallGo/thermodynamics.py
WallGo/utils.py
WallGo/PotentialTools/__init__.py
WallGo/PotentialTools/effectivePotentialNoResum.py
WallGo/PotentialTools/integrals.py
WallGo/PotentialTools/utils.py
WallGo/PotentialTools/Config/PotentialToolsDefaults.ini
WallGo/PotentialTools/Data/InterpolationTable_Jb.txt
WallGo/PotentialTools/Data/InterpolationTable_Jf.txt
wallgo-1.1.0.dist-info/licenses/LICENSE
wallgo-1.1.0.dist-info/METADATA
wallgo-1.1.0.dist-info/WHEEL
wallgo-1.1.0.dist-info/top_level.txt
wallgo-1.1.0.dist-info/RECORD
