Metadata-Version: 2.4
Name: WallGo
Version: 1.1.0
Summary: A package for computing the bubble wall speed in cosmological phase transitions.
Author-email: Andreas Ekstedt <andreas.ekstedt@physics.uu.se>, Oliver Gould <oliver.gould@nottingham.ac.uk>, Joonas Hirvonen <joonas.hirvonen@nottingham.ac.uk>, Benoit Laurent <benoit.laurent@mail.mcgill.ca>, Lauri Niemi <lauri.b.niemi@helsinki.fi>, Philipp Schicho <philipp.schicho@unige.ch>, Jorinde van de Vis <jorinde.van.de.vis@cern.ch>
License: GPL v3.0
Project-URL: Homepage, https://wallspeed.readthedocs.io/
Project-URL: Repository, https://github.com/Wall-Go/WallGo
Project-URL: Issues, https://github.com/Wall-Go/WallGo/issues
Project-URL: Changelog, https://github.com/Wall-Go/WallGo/blob/main/CHANGELOG.rst
Classifier: Intended Audience :: Science/Research
Classifier: Topic :: Scientific/Engineering :: Physics
Classifier: License :: OSI Approved :: GNU General Public License v3 (GPLv3)
Classifier: Development Status :: 3 - Alpha
Classifier: Programming Language :: Python :: 3.10
Classifier: Programming Language :: Python :: 3.11
Classifier: Programming Language :: Python :: 3.12
Classifier: Programming Language :: Python :: 3.13
Requires-Python: >=3.10
License-File: LICENSE
Requires-Dist: findiff>=0.9.2
Requires-Dist: h5py>=3.8.0
Requires-Dist: numpy>=1.21.5
Requires-Dist: scipy>=1.9.0
Provides-Extra: tests
Requires-Dist: pytest>=7.2.2; extra == "tests"
Provides-Extra: docs
Requires-Dist: graphviz; extra == "docs"
Requires-Dist: myst_parser; extra == "docs"
Requires-Dist: sphinx; extra == "docs"
Requires-Dist: sphinx-rtd-theme; extra == "docs"
Requires-Dist: sphinx-automodapi; extra == "docs"
Requires-Dist: sphinxcontrib-bibtex; extra == "docs"
Requires-Dist: WallGoCollision; extra == "docs"
Provides-Extra: lint
Requires-Dist: black; extra == "lint"
Requires-Dist: mypy; extra == "lint"
Requires-Dist: pylint; extra == "lint"
Dynamic: license-file
